<annotation>
	<folder>tmp</folder>
	<filename>183.jpg</filename>
	<path>D:\wiks\rangrang\rangrang-ML\pis\rangrang-ML\workspace\color_detection\tmp\183.jpg</path>
	<source>
		<database>Unknown</database>
	</source>
	<size>
		<width>1600</width>
		<height>1157</height>
		<depth>3</depth>
	</size>
	<segmented>0</segmented>
	<object>
		<name>putih</name>
		<pose>Unspecified</pose>
		<truncated>0</truncated>
		<difficult>0</difficult>
		<bndbox>
			<xmin>510</xmin>
			<ymin>636</ymin>
			<xmax>539</xmax>
			<ymax>713</ymax>
		</bndbox>
	</object>
	<object>
		<name>biru</name>
		<pose>Unspecified</pose>
		<truncated>0</truncated>
		<difficult>0</difficult>
		<bndbox>
			<xmin>17</xmin>
			<ymin>437</ymin>
			<xmax>74</xmax>
			<ymax>497</ymax>
		</bndbox>
	</object>
</annotation>
