<annotation>
	<folder>tmp</folder>
	<filename>243.jpg</filename>
	<path>D:\wiks\rangrang\rangrang-ML\pis\rangrang-ML\workspace\color_detection\tmp\243.jpg</path>
	<source>
		<database>Unknown</database>
	</source>
	<size>
		<width>1024</width>
		<height>1024</height>
		<depth>3</depth>
	</size>
	<segmented>0</segmented>
	<object>
		<name>kuning</name>
		<pose>Unspecified</pose>
		<truncated>0</truncated>
		<difficult>0</difficult>
		<bndbox>
			<xmin>785</xmin>
			<ymin>699</ymin>
			<xmax>970</xmax>
			<ymax>812</ymax>
		</bndbox>
	</object>
	<object>
		<name>merah</name>
		<pose>Unspecified</pose>
		<truncated>1</truncated>
		<difficult>0</difficult>
		<bndbox>
			<xmin>961</xmin>
			<ymin>654</ymin>
			<xmax>1024</xmax>
			<ymax>794</ymax>
		</bndbox>
	</object>
</annotation>
