<annotation>
	<folder>images</folder>
	<filename>152.jpg</filename>
	<path>C:\Users\Wahyu Setianto\Desktop\rangrang-ML\workspace\color_detection\images\152.jpg</path>
	<source>
		<database>Unknown</database>
	</source>
	<size>
		<width>870</width>
		<height>1153</height>
		<depth>3</depth>
	</size>
	<segmented>0</segmented>
	<object>
		<name>hitam</name>
		<pose>Unspecified</pose>
		<truncated>0</truncated>
		<difficult>0</difficult>
		<bndbox>
			<xmin>467</xmin>
			<ymin>651</ymin>
			<xmax>628</xmax>
			<ymax>718</ymax>
		</bndbox>
	</object>
	<object>
		<name>hitam</name>
		<pose>Unspecified</pose>
		<truncated>0</truncated>
		<difficult>0</difficult>
		<bndbox>
			<xmin>241</xmin>
			<ymin>653</ymin>
			<xmax>402</xmax>
			<ymax>720</ymax>
		</bndbox>
	</object>
	<object>
		<name>hitam</name>
		<pose>Unspecified</pose>
		<truncated>1</truncated>
		<difficult>0</difficult>
		<bndbox>
			<xmin>709</xmin>
			<ymin>816</ymin>
			<xmax>870</xmax>
			<ymax>917</ymax>
		</bndbox>
	</object>
	<object>
		<name>hijau</name>
		<pose>Unspecified</pose>
		<truncated>0</truncated>
		<difficult>0</difficult>
		<bndbox>
			<xmin>236</xmin>
			<ymin>634</ymin>
			<xmax>712</xmax>
			<ymax>840</ymax>
		</bndbox>
	</object>
</annotation>
